qsc/Frenet_to_cylindrical.py
qsc/__init__.py
qsc/calculate_r1.py
qsc/calculate_r2.py
qsc/calculate_r3.py
qsc/configurations.py
qsc/fourier_interpolation.py
qsc/grad_B_tensor.py
qsc/init_axis.py
qsc/mercier.py
qsc/newton.py
qsc/plot.py
qsc/qsc.py
qsc/r_singularity.py
qsc/spectral_diff_matrix.py
qsc/to_vmec.py
qsc/util.py
qsc/tests/__init__.py
qsc/tests/test_configurations.py
qsc/tests/test_fourier_interpolation.py
qsc/tests/test_grad_B_tensor.py
qsc/tests/test_iota2.py
qsc/tests/test_newton.py
qsc/tests/test_plot.py
qsc/tests/test_qsc.py
qsc/tests/test_spectral_diff_matrix.py
qsc/tests/test_to_vmec.py
qsc/tests/test_util.py
qsc-0.1.2.dist-info/LICENSE.txt
qsc-0.1.2.dist-info/METADATA
qsc-0.1.2.dist-info/WHEEL
qsc-0.1.2.dist-info/top_level.txt
qsc-0.1.2.dist-info/RECORD
