Metadata-Version: 2.1
Name: qsc
Version: 0.1.2
Summary: Quasisymmetric Stellarator Construction
Home-page: https://github.com/landreman/pyQSC
Author: Matt Landreman
Author-email: matt.landreman@gmail.com
License: UNKNOWN
Platform: UNKNOWN
Classifier: Programming Language :: Python :: 3
Classifier: License :: OSI Approved :: BSD License
Classifier: Operating System :: OS Independent
Requires-Python: >=3.6
